README.md
setup.py
uploadOss/__init__.py
uploadOss/upload_oss_file.py
uploadossfile.egg-info/PKG-INFO
uploadossfile.egg-info/SOURCES.txt
uploadossfile.egg-info/dependency_links.txt
uploadossfile.egg-info/top_level.txt
uploadossfile.egg-info/zip-safe