Metadata-Version: 1.1
Name: uploadossfile
Version: 0.1.0
Summary: upload oss file
Home-page: https://github.com
Author: ivan
Author-email: chongwuwy@163.com
License: MIT
Platform: UNKNOWN
Classifier: License :: OSI Approved :: MIT License
Classifier: Programming Language :: Python
Classifier: Intended Audience :: Developers
Classifier: Operating System :: OS Independent
